{
  "meta": {
    "source": "Naver Mobile API (6-hour pipeline)",
    "updatedAtKst": "2026-03-02 10:16:26",
    "latestTradingDate": "2026-02-27",
    "refreshIntervalHours": 6
  },
  "data": [
    {
      "date": "2025-03-06",
      "individual": -3693,
      "foreign": 1382,
      "institution": 1561,
      "financialInvestment": 1561,
      "insurance": 0,
      "investmentTrust": 0,
      "bank": 0,
      "otherFinancial": 0,
      "pension": 0,
      "otherCorporation": 750
    },
    {
      "date": "2025-03-07",
      "individual": -1941,
      "foreign": 596,
      "institution": 279,
      "financialInvestment": 279,
      "insurance": 0,
      "investmentTrust": 0,
      "bank": 0,
      "otherFinancial": 0,
      "pension": 0,
      "otherCorporation": 1066
    },
    {
      "date": "2025-03-10",
      "individual": 2097,
      "foreign": -4242,
      "institution": 1428,
      "financialInvestment": 1428,
      "insurance": 0,
      "investmentTrust": 0,
      "bank": 0,
      "otherFinancial": 0,
      "pension": 0,
      "otherCorporation": 717
    },
    {
      "date": "2025-03-11",
      "individual": 4929,
      "foreign": -15373,
      "institution": -2381,
      "financialInvestment": -2381,
      "insurance": 0,
      "investmentTrust": 0,
      "bank": 0,
      "otherFinancial": 0,
      "pension": 0,
      "otherCorporation": 12825
    },
    {
      "date": "2025-03-12",
      "individual": -5050,
      "foreign": 3790,
      "institution": 319,
      "financialInvestment": 319,
      "insurance": 0,
      "investmentTrust": 0,
      "bank": 0,
      "otherFinancial": 0,
      "pension": 0,
      "otherCorporation": 941
    },
    {
      "date": "2025-03-13",
      "individual": -737,
      "foreign": -4804,
      "institution": 4448,
      "financialInvestment": 4448,
      "insurance": 0,
      "investmentTrust": 0,
      "bank": 0,
      "otherFinancial": 0,
      "pension": 0,
      "otherCorporation": 1093
    },
    {
      "date": "2025-03-14",
      "individual": 2079,
      "foreign": -2894,
      "institution": -205,
      "financialInvestment": -205,
      "insurance": 0,
      "investmentTrust": 0,
      "bank": 0,
      "otherFinancial": 0,
      "pension": 0,
      "otherCorporation": 1020
    },
    {
      "date": "2025-03-17",
      "individual": -11804,
      "foreign": 6152,
      "institution": 4947,
      "financialInvestment": 4947,
      "insurance": 0,
      "investmentTrust": 0,
      "bank": 0,
      "otherFinancial": 0,
      "pension": 0,
      "otherCorporation": 705
    },
    {
      "date": "2025-03-18",
      "individual": -6126,
      "foreign": 4408,
      "institution": 950,
      "financialInvestment": 950,
      "insurance": 0,
      "investmentTrust": 0,
      "bank": 0,
      "otherFinancial": 0,
      "pension": 0,
      "otherCorporation": 768
    },
    {
      "date": "2025-03-19",
      "individual": -6744,
      "foreign": 3026,
      "institution": 2873,
      "financialInvestment": 2873,
      "insurance": 0,
      "investmentTrust": 0,
      "bank": 0,
      "otherFinancial": 0,
      "pension": 0,
      "otherCorporation": 845
    },
    {
      "date": "2025-03-20",
      "individual": -7013,
      "foreign": 5487,
      "institution": 664,
      "financialInvestment": 664,
      "insurance": 0,
      "investmentTrust": 0,
      "bank": 0,
      "otherFinancial": 0,
      "pension": 0,
      "otherCorporation": 862
    },
    {
      "date": "2025-03-21",
      "individual": -5379,
      "foreign": 8478,
      "institution": -4020,
      "financialInvestment": -4020,
      "insurance": 0,
      "investmentTrust": 0,
      "bank": 0,
      "otherFinancial": 0,
      "pension": 0,
      "otherCorporation": 921
    },
    {
      "date": "2025-03-24",
      "individual": -781,
      "foreign": 77,
      "institution": -288,
      "financialInvestment": -288,
      "insurance": 0,
      "investmentTrust": 0,
      "bank": 0,
      "otherFinancial": 0,
      "pension": 0,
      "otherCorporation": 992
    },
    {
      "date": "2025-03-25",
      "individual": -642,
      "foreign": -787,
      "institution": 691,
      "financialInvestment": 691,
      "insurance": 0,
      "investmentTrust": 0,
      "bank": 0,
      "otherFinancial": 0,
      "pension": 0,
      "otherCorporation": 738
    },
    {
      "date": "2025-03-26",
      "individual": -6798,
      "foreign": 3504,
      "institution": 2603,
      "financialInvestment": 2603,
      "insurance": 0,
      "investmentTrust": 0,
      "bank": 0,
      "otherFinancial": 0,
      "pension": 0,
      "otherCorporation": 691
    },
    {
      "date": "2025-03-27",
      "individual": 1196,
      "foreign": 877,
      "institution": -3152,
      "financialInvestment": -3152,
      "insurance": 0,
      "investmentTrust": 0,
      "bank": 0,
      "otherFinancial": 0,
      "pension": 0,
      "otherCorporation": 1079
    },
    {
      "date": "2025-03-28",
      "individual": 5408,
      "foreign": -6403,
      "institution": 31,
      "financialInvestment": 31,
      "insurance": 0,
      "investmentTrust": 0,
      "bank": 0,
      "otherFinancial": 0,
      "pension": 0,
      "otherCorporation": 964
    },
    {
      "date": "2025-03-31",
      "individual": 7891,
      "foreign": -15754,
      "institution": 6673,
      "financialInvestment": 6673,
      "insurance": 0,
      "investmentTrust": 0,
      "bank": 0,
      "otherFinancial": 0,
      "pension": 0,
      "otherCorporation": 1190
    },
    {
      "date": "2025-04-01",
      "individual": 866,
      "foreign": -3901,
      "institution": 1806,
      "financialInvestment": 1806,
      "insurance": 0,
      "investmentTrust": 0,
      "bank": 0,
      "otherFinancial": 0,
      "pension": 0,
      "otherCorporation": 1229
    },
    {
      "date": "2025-04-02",
      "individual": 4791,
      "foreign": -7242,
      "institution": 1480,
      "financialInvestment": 1480,
      "insurance": 0,
      "investmentTrust": 0,
      "bank": 0,
      "otherFinancial": 0,
      "pension": 0,
      "otherCorporation": 971
    },
    {
      "date": "2025-04-03",
      "individual": 8014,
      "foreign": -13752,
      "institution": 4610,
      "financialInvestment": 4610,
      "insurance": 0,
      "investmentTrust": 0,
      "bank": 0,
      "otherFinancial": 0,
      "pension": 0,
      "otherCorporation": 1128
    },
    {
      "date": "2025-04-04",
      "individual": 10770,
      "foreign": -17869,
      "institution": 6211,
      "financialInvestment": 6211,
      "insurance": 0,
      "investmentTrust": 0,
      "bank": 0,
      "otherFinancial": 0,
      "pension": 0,
      "otherCorporation": 888
    },
    {
      "date": "2025-04-07",
      "individual": 16721,
      "foreign": -20957,
      "institution": 2571,
      "financialInvestment": 2571,
      "insurance": 0,
      "investmentTrust": 0,
      "bank": 0,
      "otherFinancial": 0,
      "pension": 0,
      "otherCorporation": 1665
    },
    {
      "date": "2025-04-08",
      "individual": 6029,
      "foreign": -6425,
      "institution": -898,
      "financialInvestment": -898,
      "insurance": 0,
      "investmentTrust": 0,
      "bank": 0,
      "otherFinancial": 0,
      "pension": 0,
      "otherCorporation": 1294
    },
    {
      "date": "2025-04-09",
      "individual": 9389,
      "foreign": -10007,
      "institution": -698,
      "financialInvestment": -698,
      "insurance": 0,
      "investmentTrust": 0,
      "bank": 0,
      "otherFinancial": 0,
      "pension": 0,
      "otherCorporation": 1316
    },
    {
      "date": "2025-04-10",
      "individual": -10693,
      "foreign": 3287,
      "institution": 6682,
      "financialInvestment": 6682,
      "insurance": 0,
      "investmentTrust": 0,
      "bank": 0,
      "otherFinancial": 0,
      "pension": 0,
      "otherCorporation": 724
    },
    {
      "date": "2025-04-11",
      "individual": 4339,
      "foreign": -6888,
      "institution": 1378,
      "financialInvestment": 1378,
      "insurance": 0,
      "investmentTrust": 0,
      "bank": 0,
      "otherFinancial": 0,
      "pension": 0,
      "otherCorporation": 1171
    },
    {
      "date": "2025-04-14",
      "individual": 1939,
      "foreign": -2420,
      "institution": -67,
      "financialInvestment": -67,
      "insurance": 0,
      "investmentTrust": 0,
      "bank": 0,
      "otherFinancial": 0,
      "pension": 0,
      "otherCorporation": 548
    },
    {
      "date": "2025-04-15",
      "individual": -1468,
      "foreign": -1177,
      "institution": 1831,
      "financialInvestment": 1831,
      "insurance": 0,
      "investmentTrust": 0,
      "bank": 0,
      "otherFinancial": 0,
      "pension": 0,
      "otherCorporation": 814
    },
    {
      "date": "2025-04-16",
      "individual": 3835,
      "foreign": -4577,
      "institution": -153,
      "financialInvestment": -153,
      "insurance": 0,
      "investmentTrust": 0,
      "bank": 0,
      "otherFinancial": 0,
      "pension": 0,
      "otherCorporation": 895
    },
    {
      "date": "2025-04-17",
      "individual": -1102,
      "foreign": -3519,
      "institution": 3689,
      "financialInvestment": 3689,
      "insurance": 0,
      "investmentTrust": 0,
      "bank": 0,
      "otherFinancial": 0,
      "pension": 0,
      "otherCorporation": 932
    },
    {
      "date": "2025-04-18",
      "individual": -223,
      "foreign": -1052,
      "institution": 816,
      "financialInvestment": 816,
      "insurance": 0,
      "investmentTrust": 0,
      "bank": 0,
      "otherFinancial": 0,
      "pension": 0,
      "otherCorporation": 459
    },
    {
      "date": "2025-04-21",
      "individual": 1864,
      "foreign": -2886,
      "institution": 234,
      "financialInvestment": 234,
      "insurance": 0,
      "investmentTrust": 0,
      "bank": 0,
      "otherFinancial": 0,
      "pension": 0,
      "otherCorporation": 788
    },
    {
      "date": "2025-04-22",
      "individual": 1667,
      "foreign": -2430,
      "institution": 107,
      "financialInvestment": 107,
      "insurance": 0,
      "investmentTrust": 0,
      "bank": 0,
      "otherFinancial": 0,
      "pension": 0,
      "otherCorporation": 656
    },
    {
      "date": "2025-04-23",
      "individual": -5485,
      "foreign": -1977,
      "institution": 6866,
      "financialInvestment": 6866,
      "insurance": 0,
      "investmentTrust": 0,
      "bank": 0,
      "otherFinancial": 0,
      "pension": 0,
      "otherCorporation": 596
    },
    {
      "date": "2025-04-24",
      "individual": 1351,
      "foreign": -77,
      "institution": -1987,
      "financialInvestment": -1987,
      "insurance": 0,
      "investmentTrust": 0,
      "bank": 0,
      "otherFinancial": 0,
      "pension": 0,
      "otherCorporation": 713
    },
    {
      "date": "2025-04-25",
      "individual": -7741,
      "foreign": 6126,
      "institution": 5072,
      "financialInvestment": 5072,
      "insurance": 0,
      "investmentTrust": 0,
      "bank": 0,
      "otherFinancial": 0,
      "pension": 0,
      "otherCorporation": -3457
    },
    {
      "date": "2025-04-28",
      "individual": -496,
      "foreign": -854,
      "institution": 916,
      "financialInvestment": 916,
      "insurance": 0,
      "investmentTrust": 0,
      "bank": 0,
      "otherFinancial": 0,
      "pension": 0,
      "otherCorporation": 434
    },
    {
      "date": "2025-04-29",
      "individual": -1591,
      "foreign": 6925,
      "institution": -5804,
      "financialInvestment": -5804,
      "insurance": 0,
      "investmentTrust": 0,
      "bank": 0,
      "otherFinancial": 0,
      "pension": 0,
      "otherCorporation": 470
    },
    {
      "date": "2025-04-30",
      "individual": 3055,
      "foreign": -1688,
      "institution": -2210,
      "financialInvestment": -2210,
      "insurance": 0,
      "investmentTrust": 0,
      "bank": 0,
      "otherFinancial": 0,
      "pension": 0,
      "otherCorporation": 843
    },
    {
      "date": "2025-05-02",
      "individual": -2349,
      "foreign": -1702,
      "institution": 3228,
      "financialInvestment": 3228,
      "insurance": 0,
      "investmentTrust": 0,
      "bank": 0,
      "otherFinancial": 0,
      "pension": 0,
      "otherCorporation": 823
    },
    {
      "date": "2025-05-07",
      "individual": -4646,
      "foreign": 3488,
      "institution": 869,
      "financialInvestment": 869,
      "insurance": 0,
      "investmentTrust": 0,
      "bank": 0,
      "otherFinancial": 0,
      "pension": 0,
      "otherCorporation": 289
    },
    {
      "date": "2025-05-08",
      "individual": -13,
      "foreign": 1303,
      "institution": -1898,
      "financialInvestment": -1898,
      "insurance": 0,
      "investmentTrust": 0,
      "bank": 0,
      "otherFinancial": 0,
      "pension": 0,
      "otherCorporation": 608
    },
    {
      "date": "2025-05-09",
      "individual": 632,
      "foreign": 675,
      "institution": -1873,
      "financialInvestment": -1873,
      "insurance": 0,
      "investmentTrust": 0,
      "bank": 0,
      "otherFinancial": 0,
      "pension": 0,
      "otherCorporation": 566
    },
    {
      "date": "2025-05-12",
      "individual": -3907,
      "foreign": -71,
      "institution": 3429,
      "financialInvestment": 3429,
      "insurance": 0,
      "investmentTrust": 0,
      "bank": 0,
      "otherFinancial": 0,
      "pension": 0,
      "otherCorporation": 549
    },
    {
      "date": "2025-05-13",
      "individual": -1360,
      "foreign": 1714,
      "institution": -893,
      "financialInvestment": -893,
      "insurance": 0,
      "investmentTrust": 0,
      "bank": 0,
      "otherFinancial": 0,
      "pension": 0,
      "otherCorporation": 539
    },
    {
      "date": "2025-05-14",
      "individual": -10024,
      "foreign": 4704,
      "institution": 5348,
      "financialInvestment": 5348,
      "insurance": 0,
      "investmentTrust": 0,
      "bank": 0,
      "otherFinancial": 0,
      "pension": 0,
      "otherCorporation": -28
    },
    {
      "date": "2025-05-15",
      "individual": 460,
      "foreign": 2723,
      "institution": -3681,
      "financialInvestment": -3681,
      "insurance": 0,
      "investmentTrust": 0,
      "bank": 0,
      "otherFinancial": 0,
      "pension": 0,
      "otherCorporation": 498
    },
    {
      "date": "2025-05-16",
      "individual": -2823,
      "foreign": 1694,
      "institution": 1134,
      "financialInvestment": 1134,
      "insurance": 0,
      "investmentTrust": 0,
      "bank": 0,
      "otherFinancial": 0,
      "pension": 0,
      "otherCorporation": -5
    },
    {
      "date": "2025-05-19",
      "individual": 2986,
      "foreign": -1134,
      "institution": -1948,
      "financialInvestment": -1948,
      "insurance": 0,
      "investmentTrust": 0,
      "bank": 0,
      "otherFinancial": 0,
      "pension": 0,
      "otherCorporation": 96
    },
    {
      "date": "2025-05-20",
      "individual": 206,
      "foreign": -1145,
      "institution": 610,
      "financialInvestment": 610,
      "insurance": 0,
      "investmentTrust": 0,
      "bank": 0,
      "otherFinancial": 0,
      "pension": 0,
      "otherCorporation": 329
    },
    {
      "date": "2025-05-21",
      "individual": -3315,
      "foreign": 1920,
      "institution": 1046,
      "financialInvestment": 1046,
      "insurance": 0,
      "investmentTrust": 0,
      "bank": 0,
      "otherFinancial": 0,
      "pension": 0,
      "otherCorporation": 349
    },
    {
      "date": "2025-05-22",
      "individual": 6848,
      "foreign": -2237,
      "institution": -4319,
      "financialInvestment": -4319,
      "insurance": 0,
      "investmentTrust": 0,
      "bank": 0,
      "otherFinancial": 0,
      "pension": 0,
      "otherCorporation": -292
    },
    {
      "date": "2025-05-23",
      "individual": 1347,
      "foreign": -585,
      "institution": -1026,
      "financialInvestment": -1026,
      "insurance": 0,
      "investmentTrust": 0,
      "bank": 0,
      "otherFinancial": 0,
      "pension": 0,
      "otherCorporation": 264
    },
    {
      "date": "2025-05-26",
      "individual": -5158,
      "foreign": 1015,
      "institution": 4323,
      "financialInvestment": 4323,
      "insurance": 0,
      "investmentTrust": 0,
      "bank": 0,
      "otherFinancial": 0,
      "pension": 0,
      "otherCorporation": -180
    },
    {
      "date": "2025-05-27",
      "individual": 537,
      "foreign": -781,
      "institution": -201,
      "financialInvestment": -201,
      "insurance": 0,
      "investmentTrust": 0,
      "bank": 0,
      "otherFinancial": 0,
      "pension": 0,
      "otherCorporation": 445
    },
    {
      "date": "2025-05-28",
      "individual": -9907,
      "foreign": 2999,
      "institution": 7438,
      "financialInvestment": 7438,
      "insurance": 0,
      "investmentTrust": 0,
      "bank": 0,
      "otherFinancial": 0,
      "pension": 0,
      "otherCorporation": -530
    },
    {
      "date": "2025-05-29",
      "individual": -9963,
      "foreign": 2897,
      "institution": 6842,
      "financialInvestment": 6842,
      "insurance": 0,
      "investmentTrust": 0,
      "bank": 0,
      "otherFinancial": 0,
      "pension": 0,
      "otherCorporation": 224
    },
    {
      "date": "2025-05-30",
      "individual": 6051,
      "foreign": -6070,
      "institution": -160,
      "financialInvestment": -160,
      "insurance": 0,
      "investmentTrust": 0,
      "bank": 0,
      "otherFinancial": 0,
      "pension": 0,
      "otherCorporation": 179
    },
    {
      "date": "2025-06-02",
      "individual": 982,
      "foreign": 1250,
      "institution": -2415,
      "financialInvestment": -2415,
      "insurance": 0,
      "investmentTrust": 0,
      "bank": 0,
      "otherFinancial": 0,
      "pension": 0,
      "otherCorporation": 183
    },
    {
      "date": "2025-06-04",
      "individual": -12260,
      "foreign": 10507,
      "institution": 2046,
      "financialInvestment": 2046,
      "insurance": 0,
      "investmentTrust": 0,
      "bank": 0,
      "otherFinancial": 0,
      "pension": 0,
      "otherCorporation": -293
    },
    {
      "date": "2025-06-05",
      "individual": -11892,
      "foreign": 9801,
      "institution": 2207,
      "financialInvestment": 2207,
      "insurance": 0,
      "investmentTrust": 0,
      "bank": 0,
      "otherFinancial": 0,
      "pension": 0,
      "otherCorporation": -116
    },
    {
      "date": "2025-06-09",
      "individual": -2301,
      "foreign": 9767,
      "institution": -7332,
      "financialInvestment": -7332,
      "insurance": 0,
      "investmentTrust": 0,
      "bank": 0,
      "otherFinancial": 0,
      "pension": 0,
      "otherCorporation": -134
    },
    {
      "date": "2025-06-10",
      "individual": -6269,
      "foreign": 6323,
      "institution": 142,
      "financialInvestment": 142,
      "insurance": 0,
      "investmentTrust": 0,
      "bank": 0,
      "otherFinancial": 0,
      "pension": 0,
      "otherCorporation": -196
    },
    {
      "date": "2025-06-11",
      "individual": -3663,
      "foreign": 1661,
      "institution": 2304,
      "financialInvestment": 2304,
      "insurance": 0,
      "investmentTrust": 0,
      "bank": 0,
      "otherFinancial": 0,
      "pension": 0,
      "otherCorporation": -302
    },
    {
      "date": "2025-06-12",
      "individual": -1794,
      "foreign": 4073,
      "institution": -2304,
      "financialInvestment": -2304,
      "insurance": 0,
      "investmentTrust": 0,
      "bank": 0,
      "otherFinancial": 0,
      "pension": 0,
      "otherCorporation": 25
    },
    {
      "date": "2025-06-13",
      "individual": 4674,
      "foreign": 1210,
      "institution": -6461,
      "financialInvestment": -6461,
      "insurance": 0,
      "investmentTrust": 0,
      "bank": 0,
      "otherFinancial": 0,
      "pension": 0,
      "otherCorporation": 577
    },
    {
      "date": "2025-06-16",
      "individual": 463,
      "foreign": -3224,
      "institution": 2524,
      "financialInvestment": 2524,
      "insurance": 0,
      "investmentTrust": 0,
      "bank": 0,
      "otherFinancial": 0,
      "pension": 0,
      "otherCorporation": 237
    },
    {
      "date": "2025-06-17",
      "individual": 2245,
      "foreign": -953,
      "institution": -1006,
      "financialInvestment": -1006,
      "insurance": 0,
      "investmentTrust": 0,
      "bank": 0,
      "otherFinancial": 0,
      "pension": 0,
      "otherCorporation": -286
    },
    {
      "date": "2025-06-18",
      "individual": -4318,
      "foreign": 2870,
      "institution": 1101,
      "financialInvestment": 1101,
      "insurance": 0,
      "investmentTrust": 0,
      "bank": 0,
      "otherFinancial": 0,
      "pension": 0,
      "otherCorporation": 347
    },
    {
      "date": "2025-06-19",
      "individual": 3500,
      "foreign": -826,
      "institution": -3018,
      "financialInvestment": -3018,
      "insurance": 0,
      "investmentTrust": 0,
      "bank": 0,
      "otherFinancial": 0,
      "pension": 0,
      "otherCorporation": 344
    },
    {
      "date": "2025-06-20",
      "individual": -5966,
      "foreign": 5626,
      "institution": 372,
      "financialInvestment": 372,
      "insurance": 0,
      "investmentTrust": 0,
      "bank": 0,
      "otherFinancial": 0,
      "pension": 0,
      "otherCorporation": -32
    },
    {
      "date": "2025-06-23",
      "individual": 13797,
      "foreign": -3668,
      "institution": -9485,
      "financialInvestment": -9485,
      "insurance": 0,
      "investmentTrust": 0,
      "bank": 0,
      "otherFinancial": 0,
      "pension": 0,
      "otherCorporation": -644
    },
    {
      "date": "2025-06-24",
      "individual": -5676,
      "foreign": 4383,
      "institution": 2594,
      "financialInvestment": 2594,
      "insurance": 0,
      "investmentTrust": 0,
      "bank": 0,
      "otherFinancial": 0,
      "pension": 0,
      "otherCorporation": -1301
    },
    {
      "date": "2025-06-25",
      "individual": 7580,
      "foreign": -1108,
      "institution": -5883,
      "financialInvestment": -5883,
      "insurance": 0,
      "investmentTrust": 0,
      "bank": 0,
      "otherFinancial": 0,
      "pension": 0,
      "otherCorporation": -589
    },
    {
      "date": "2025-06-26",
      "individual": 8325,
      "foreign": -5794,
      "institution": -4080,
      "financialInvestment": -4080,
      "insurance": 0,
      "investmentTrust": 0,
      "bank": 0,
      "otherFinancial": 0,
      "pension": 0,
      "otherCorporation": 1549
    },
    {
      "date": "2025-06-27",
      "individual": 4868,
      "foreign": -8580,
      "institution": 3434,
      "financialInvestment": 3434,
      "insurance": 0,
      "investmentTrust": 0,
      "bank": 0,
      "otherFinancial": 0,
      "pension": 0,
      "otherCorporation": 278
    },
    {
      "date": "2025-06-30",
      "individual": 1892,
      "foreign": -6489,
      "institution": 4757,
      "financialInvestment": 4757,
      "insurance": 0,
      "investmentTrust": 0,
      "bank": 0,
      "otherFinancial": 0,
      "pension": 0,
      "otherCorporation": -160
    },
    {
      "date": "2025-07-01",
      "individual": -6405,
      "foreign": 1760,
      "institution": 4745,
      "financialInvestment": 4745,
      "insurance": 0,
      "investmentTrust": 0,
      "bank": 0,
      "otherFinancial": 0,
      "pension": 0,
      "otherCorporation": -100
    },
    {
      "date": "2025-07-02",
      "individual": 2329,
      "foreign": -3278,
      "institution": 720,
      "financialInvestment": 720,
      "insurance": 0,
      "investmentTrust": 0,
      "bank": 0,
      "otherFinancial": 0,
      "pension": 0,
      "otherCorporation": 229
    },
    {
      "date": "2025-07-03",
      "individual": -12330,
      "foreign": 6427,
      "institution": 5484,
      "financialInvestment": 5484,
      "insurance": 0,
      "investmentTrust": 0,
      "bank": 0,
      "otherFinancial": 0,
      "pension": 0,
      "otherCorporation": 419
    },
    {
      "date": "2025-07-04",
      "individual": 2575,
      "foreign": 1624,
      "institution": -3822,
      "financialInvestment": -3822,
      "insurance": 0,
      "investmentTrust": 0,
      "bank": 0,
      "otherFinancial": 0,
      "pension": 0,
      "otherCorporation": -377
    },
    {
      "date": "2025-07-07",
      "individual": 1558,
      "foreign": -937,
      "institution": -811,
      "financialInvestment": -811,
      "insurance": 0,
      "investmentTrust": 0,
      "bank": 0,
      "otherFinancial": 0,
      "pension": 0,
      "otherCorporation": 190
    },
    {
      "date": "2025-07-08",
      "individual": -2549,
      "foreign": 2461,
      "institution": -326,
      "financialInvestment": -326,
      "insurance": 0,
      "investmentTrust": 0,
      "bank": 0,
      "otherFinancial": 0,
      "pension": 0,
      "otherCorporation": 414
    },
    {
      "date": "2025-07-09",
      "individual": 4310,
      "foreign": -4105,
      "institution": -571,
      "financialInvestment": -571,
      "insurance": 0,
      "investmentTrust": 0,
      "bank": 0,
      "otherFinancial": 0,
      "pension": 0,
      "otherCorporation": 366
    },
    {
      "date": "2025-07-10",
      "individual": -5869,
      "foreign": 4694,
      "institution": 447,
      "financialInvestment": 447,
      "insurance": 0,
      "investmentTrust": 0,
      "bank": 0,
      "otherFinancial": 0,
      "pension": 0,
      "otherCorporation": 728
    },
    {
      "date": "2025-07-11",
      "individual": 1250,
      "foreign": 3259,
      "institution": -743,
      "financialInvestment": -743,
      "insurance": 0,
      "investmentTrust": 0,
      "bank": 0,
      "otherFinancial": 0,
      "pension": 0,
      "otherCorporation": -3766
    },
    {
      "date": "2025-07-14",
      "individual": -3568,
      "foreign": 3707,
      "institution": -947,
      "financialInvestment": -947,
      "insurance": 0,
      "investmentTrust": 0,
      "bank": 0,
      "otherFinancial": 0,
      "pension": 0,
      "otherCorporation": 808
    },
    {
      "date": "2025-07-15",
      "individual": -3102,
      "foreign": 2123,
      "institution": -167,
      "financialInvestment": -167,
      "insurance": 0,
      "investmentTrust": 0,
      "bank": 0,
      "otherFinancial": 0,
      "pension": 0,
      "otherCorporation": 1146
    },
    {
      "date": "2025-07-16",
      "individual": 4016,
      "foreign": 555,
      "institution": -5525,
      "financialInvestment": -5525,
      "insurance": 0,
      "investmentTrust": 0,
      "bank": 0,
      "otherFinancial": 0,
      "pension": 0,
      "otherCorporation": 954
    },
    {
      "date": "2025-07-17",
      "individual": -3356,
      "foreign": 493,
      "institution": 1583,
      "financialInvestment": 1583,
      "insurance": 0,
      "investmentTrust": 0,
      "bank": 0,
      "otherFinancial": 0,
      "pension": 0,
      "otherCorporation": 1280
    },
    {
      "date": "2025-07-18",
      "individual": -3411,
      "foreign": 1878,
      "institution": 320,
      "financialInvestment": 320,
      "insurance": 0,
      "investmentTrust": 0,
      "bank": 0,
      "otherFinancial": 0,
      "pension": 0,
      "otherCorporation": 1213
    },
    {
      "date": "2025-07-21",
      "individual": -10578,
      "foreign": 8935,
      "institution": 994,
      "financialInvestment": 994,
      "insurance": 0,
      "investmentTrust": 0,
      "bank": 0,
      "otherFinancial": 0,
      "pension": 0,
      "otherCorporation": 649
    },
    {
      "date": "2025-07-22",
      "individual": 4780,
      "foreign": -1288,
      "institution": -4128,
      "financialInvestment": -4128,
      "insurance": 0,
      "investmentTrust": 0,
      "bank": 0,
      "otherFinancial": 0,
      "pension": 0,
      "otherCorporation": 636
    },
    {
      "date": "2025-07-23",
      "individual": -6982,
      "foreign": 4228,
      "institution": 1917,
      "financialInvestment": 1917,
      "insurance": 0,
      "investmentTrust": 0,
      "bank": 0,
      "otherFinancial": 0,
      "pension": 0,
      "otherCorporation": 837
    },
    {
      "date": "2025-07-24",
      "individual": -9513,
      "foreign": 7386,
      "institution": 1273,
      "financialInvestment": 1273,
      "insurance": 0,
      "investmentTrust": 0,
      "bank": 0,
      "otherFinancial": 0,
      "pension": 0,
      "otherCorporation": 854
    },
    {
      "date": "2025-07-25",
      "individual": -4616,
      "foreign": 2706,
      "institution": 1100,
      "financialInvestment": 1100,
      "insurance": 0,
      "investmentTrust": 0,
      "bank": 0,
      "otherFinancial": 0,
      "pension": 0,
      "otherCorporation": 810
    },
    {
      "date": "2025-07-28",
      "individual": -9975,
      "foreign": 4753,
      "institution": 4520,
      "financialInvestment": 4520,
      "insurance": 0,
      "investmentTrust": 0,
      "bank": 0,
      "otherFinancial": 0,
      "pension": 0,
      "otherCorporation": 702
    },
    {
      "date": "2025-07-29",
      "individual": -8259,
      "foreign": 6054,
      "institution": 1167,
      "financialInvestment": 1167,
      "insurance": 0,
      "investmentTrust": 0,
      "bank": 0,
      "otherFinancial": 0,
      "pension": 0,
      "otherCorporation": 1038
    },
    {
      "date": "2025-07-30",
      "individual": -9844,
      "foreign": 5783,
      "institution": 3307,
      "financialInvestment": 3307,
      "insurance": 0,
      "investmentTrust": 0,
      "bank": 0,
      "otherFinancial": 0,
      "pension": 0,
      "otherCorporation": 754
    },
    {
      "date": "2025-07-31",
      "individual": 2235,
      "foreign": 3450,
      "institution": -7053,
      "financialInvestment": -7053,
      "insurance": 0,
      "investmentTrust": 0,
      "bank": 0,
      "otherFinancial": 0,
      "pension": 0,
      "otherCorporation": 1368
    },
    {
      "date": "2025-08-01",
      "individual": 16283,
      "foreign": -6524,
      "institution": -10720,
      "financialInvestment": -10720,
      "insurance": 0,
      "investmentTrust": 0,
      "bank": 0,
      "otherFinancial": 0,
      "pension": 0,
      "otherCorporation": 961
    },
    {
      "date": "2025-08-04",
      "individual": -2996,
      "foreign": 830,
      "institution": 1316,
      "financialInvestment": 1316,
      "insurance": 0,
      "investmentTrust": 0,
      "bank": 0,
      "otherFinancial": 0,
      "pension": 0,
      "otherCorporation": 850
    },
    {
      "date": "2025-08-05",
      "individual": -4785,
      "foreign": 2919,
      "institution": 947,
      "financialInvestment": 947,
      "insurance": 0,
      "investmentTrust": 0,
      "bank": 0,
      "otherFinancial": 0,
      "pension": 0,
      "otherCorporation": 919
    },
    {
      "date": "2025-08-06",
      "individual": 474,
      "foreign": 2804,
      "institution": -4020,
      "financialInvestment": -4020,
      "insurance": 0,
      "investmentTrust": 0,
      "bank": 0,
      "otherFinancial": 0,
      "pension": 0,
      "otherCorporation": 742
    },
    {
      "date": "2025-08-07",
      "individual": -2048,
      "foreign": -171,
      "institution": 1092,
      "financialInvestment": 1092,
      "insurance": 0,
      "investmentTrust": 0,
      "bank": 0,
      "otherFinancial": 0,
      "pension": 0,
      "otherCorporation": 1127
    },
    {
      "date": "2025-08-08",
      "individual": 1835,
      "foreign": -1576,
      "institution": -1318,
      "financialInvestment": -1318,
      "insurance": 0,
      "investmentTrust": 0,
      "bank": 0,
      "otherFinancial": 0,
      "pension": 0,
      "otherCorporation": 1059
    },
    {
      "date": "2025-08-11",
      "individual": -1407,
      "foreign": 2169,
      "institution": -2160,
      "financialInvestment": -2160,
      "insurance": 0,
      "investmentTrust": 0,
      "bank": 0,
      "otherFinancial": 0,
      "pension": 0,
      "otherCorporation": 1398
    },
    {
      "date": "2025-08-12",
      "individual": 634,
      "foreign": -604,
      "institution": -981,
      "financialInvestment": -981,
      "insurance": 0,
      "investmentTrust": 0,
      "bank": 0,
      "otherFinancial": 0,
      "pension": 0,
      "otherCorporation": 951
    },
    {
      "date": "2025-08-13",
      "individual": -6648,
      "foreign": 6349,
      "institution": -809,
      "financialInvestment": -809,
      "insurance": 0,
      "investmentTrust": 0,
      "bank": 0,
      "otherFinancial": 0,
      "pension": 0,
      "otherCorporation": 1108
    },
    {
      "date": "2025-08-14",
      "individual": -534,
      "foreign": -779,
      "institution": 197,
      "financialInvestment": 197,
      "insurance": 0,
      "investmentTrust": 0,
      "bank": 0,
      "otherFinancial": 0,
      "pension": 0,
      "otherCorporation": 1116
    },
    {
      "date": "2025-08-18",
      "individual": 3570,
      "foreign": -4881,
      "institution": 813,
      "financialInvestment": 813,
      "insurance": 0,
      "investmentTrust": 0,
      "bank": 0,
      "otherFinancial": 0,
      "pension": 0,
      "otherCorporation": 498
    },
    {
      "date": "2025-08-19",
      "individual": 904,
      "foreign": -4544,
      "institution": 2539,
      "financialInvestment": 2539,
      "insurance": 0,
      "investmentTrust": 0,
      "bank": 0,
      "otherFinancial": 0,
      "pension": 0,
      "otherCorporation": 1101
    },
    {
      "date": "2025-08-20",
      "individual": -3929,
      "foreign": -2185,
      "institution": 5024,
      "financialInvestment": 5024,
      "insurance": 0,
      "investmentTrust": 0,
      "bank": 0,
      "otherFinancial": 0,
      "pension": 0,
      "otherCorporation": 1090
    },
    {
      "date": "2025-08-21",
      "individual": -2591,
      "foreign": -152,
      "institution": 1598,
      "financialInvestment": 1598,
      "insurance": 0,
      "investmentTrust": 0,
      "bank": 0,
      "otherFinancial": 0,
      "pension": 0,
      "otherCorporation": 1145
    },
    {
      "date": "2025-08-22",
      "individual": -4572,
      "foreign": 1826,
      "institution": 1556,
      "financialInvestment": 1556,
      "insurance": 0,
      "investmentTrust": 0,
      "bank": 0,
      "otherFinancial": 0,
      "pension": 0,
      "otherCorporation": 1190
    },
    {
      "date": "2025-08-25",
      "individual": -3857,
      "foreign": 1224,
      "institution": 1543,
      "financialInvestment": 1543,
      "insurance": 0,
      "investmentTrust": 0,
      "bank": 0,
      "otherFinancial": 0,
      "pension": 0,
      "otherCorporation": 1090
    },
    {
      "date": "2025-08-26",
      "individual": 8519,
      "foreign": -6836,
      "institution": -2657,
      "financialInvestment": -2657,
      "insurance": 0,
      "investmentTrust": 0,
      "bank": 0,
      "otherFinancial": 0,
      "pension": 0,
      "otherCorporation": 974
    },
    {
      "date": "2025-08-27",
      "individual": 569,
      "foreign": -2023,
      "institution": 277,
      "financialInvestment": 277,
      "insurance": 0,
      "investmentTrust": 0,
      "bank": 0,
      "otherFinancial": 0,
      "pension": 0,
      "otherCorporation": 1177
    },
    {
      "date": "2025-08-28",
      "individual": -3939,
      "foreign": -241,
      "institution": 3264,
      "financialInvestment": 3264,
      "insurance": 0,
      "investmentTrust": 0,
      "bank": 0,
      "otherFinancial": 0,
      "pension": 0,
      "otherCorporation": 916
    },
    {
      "date": "2025-08-29",
      "individual": 2353,
      "foreign": -3724,
      "institution": 648,
      "financialInvestment": 648,
      "insurance": 0,
      "investmentTrust": 0,
      "bank": 0,
      "otherFinancial": 0,
      "pension": 0,
      "otherCorporation": 723
    },
    {
      "date": "2025-09-01",
      "individual": 3469,
      "foreign": -2720,
      "institution": -1940,
      "financialInvestment": -1940,
      "insurance": 0,
      "investmentTrust": 0,
      "bank": 0,
      "otherFinancial": 0,
      "pension": 0,
      "otherCorporation": 1191
    },
    {
      "date": "2025-09-02",
      "individual": -3474,
      "foreign": 4010,
      "institution": -1416,
      "financialInvestment": -1416,
      "insurance": 0,
      "investmentTrust": 0,
      "bank": 0,
      "otherFinancial": 0,
      "pension": 0,
      "otherCorporation": 880
    },
    {
      "date": "2025-09-03",
      "individual": -1563,
      "foreign": 4359,
      "institution": -3756,
      "financialInvestment": -3756,
      "insurance": 0,
      "investmentTrust": 0,
      "bank": 0,
      "otherFinancial": 0,
      "pension": 0,
      "otherCorporation": 960
    },
    {
      "date": "2025-09-04",
      "individual": -2847,
      "foreign": 2025,
      "institution": -232,
      "financialInvestment": -232,
      "insurance": 0,
      "investmentTrust": 0,
      "bank": 0,
      "otherFinancial": 0,
      "pension": 0,
      "otherCorporation": 1054
    },
    {
      "date": "2025-09-05",
      "individual": -552,
      "foreign": -1374,
      "institution": 1124,
      "financialInvestment": 1124,
      "insurance": 0,
      "investmentTrust": 0,
      "bank": 0,
      "otherFinancial": 0,
      "pension": 0,
      "otherCorporation": 802
    },
    {
      "date": "2025-09-08",
      "individual": -3848,
      "foreign": 2301,
      "institution": 778,
      "financialInvestment": 778,
      "insurance": 0,
      "investmentTrust": 0,
      "bank": 0,
      "otherFinancial": 0,
      "pension": 0,
      "otherCorporation": 769
    },
    {
      "date": "2025-09-09",
      "individual": -10371,
      "foreign": 6808,
      "institution": 2806,
      "financialInvestment": 2806,
      "insurance": 0,
      "investmentTrust": 0,
      "bank": 0,
      "otherFinancial": 0,
      "pension": 0,
      "otherCorporation": 757
    },
    {
      "date": "2025-09-10",
      "individual": -22634,
      "foreign": 13817,
      "institution": 9046,
      "financialInvestment": 9046,
      "insurance": 0,
      "investmentTrust": 0,
      "bank": 0,
      "otherFinancial": 0,
      "pension": 0,
      "otherCorporation": -229
    },
    {
      "date": "2025-09-11",
      "individual": -11493,
      "foreign": 3000,
      "institution": 8225,
      "financialInvestment": 8225,
      "insurance": 0,
      "investmentTrust": 0,
      "bank": 0,
      "otherFinancial": 0,
      "pension": 0,
      "otherCorporation": 268
    },
    {
      "date": "2025-09-12",
      "individual": -20287,
      "foreign": 14355,
      "institution": 6119,
      "financialInvestment": 6119,
      "insurance": 0,
      "investmentTrust": 0,
      "bank": 0,
      "otherFinancial": 0,
      "pension": 0,
      "otherCorporation": -187
    },
    {
      "date": "2025-09-15",
      "individual": -1374,
      "foreign": 2667,
      "institution": -1376,
      "financialInvestment": -1376,
      "insurance": 0,
      "investmentTrust": 0,
      "bank": 0,
      "otherFinancial": 0,
      "pension": 0,
      "otherCorporation": 83
    },
    {
      "date": "2025-09-16",
      "individual": -17637,
      "foreign": 17927,
      "institution": 1083,
      "financialInvestment": 1083,
      "insurance": 0,
      "investmentTrust": 0,
      "bank": 0,
      "otherFinancial": 0,
      "pension": 0,
      "otherCorporation": -1373
    },
    {
      "date": "2025-09-17",
      "individual": 2522,
      "foreign": -347,
      "institution": -3075,
      "financialInvestment": -3075,
      "insurance": 0,
      "investmentTrust": 0,
      "bank": 0,
      "otherFinancial": 0,
      "pension": 0,
      "otherCorporation": 900
    },
    {
      "date": "2025-09-18",
      "individual": -7816,
      "foreign": 2851,
      "institution": 4294,
      "financialInvestment": 4294,
      "insurance": 0,
      "investmentTrust": 0,
      "bank": 0,
      "otherFinancial": 0,
      "pension": 0,
      "otherCorporation": 671
    },
    {
      "date": "2025-09-19",
      "individual": 5332,
      "foreign": -3080,
      "institution": -3357,
      "financialInvestment": -3357,
      "insurance": 0,
      "investmentTrust": 0,
      "bank": 0,
      "otherFinancial": 0,
      "pension": 0,
      "otherCorporation": 1105
    },
    {
      "date": "2025-09-22",
      "individual": -7682,
      "foreign": 5653,
      "institution": 2672,
      "financialInvestment": 2672,
      "insurance": 0,
      "investmentTrust": 0,
      "bank": 0,
      "otherFinancial": 0,
      "pension": 0,
      "otherCorporation": -643
    },
    {
      "date": "2025-09-23",
      "individual": -2462,
      "foreign": 3414,
      "institution": -1363,
      "financialInvestment": -1363,
      "insurance": 0,
      "investmentTrust": 0,
      "bank": 0,
      "otherFinancial": 0,
      "pension": 0,
      "otherCorporation": 411
    },
    {
      "date": "2025-09-24",
      "individual": 17,
      "foreign": -2486,
      "institution": 2124,
      "financialInvestment": 2124,
      "insurance": 0,
      "investmentTrust": 0,
      "bank": 0,
      "otherFinancial": 0,
      "pension": 0,
      "otherCorporation": 345
    },
    {
      "date": "2025-09-25",
      "individual": -5411,
      "foreign": 2196,
      "institution": 2707,
      "financialInvestment": 2707,
      "insurance": 0,
      "investmentTrust": 0,
      "bank": 0,
      "otherFinancial": 0,
      "pension": 0,
      "otherCorporation": 508
    },
    {
      "date": "2025-09-26",
      "individual": 10997,
      "foreign": -5707,
      "institution": -4892,
      "financialInvestment": -4892,
      "insurance": 0,
      "investmentTrust": 0,
      "bank": 0,
      "otherFinancial": 0,
      "pension": 0,
      "otherCorporation": -398
    },
    {
      "date": "2025-09-29",
      "individual": -7480,
      "foreign": 4472,
      "institution": 3014,
      "financialInvestment": 3014,
      "insurance": 0,
      "investmentTrust": 0,
      "bank": 0,
      "otherFinancial": 0,
      "pension": 0,
      "otherCorporation": -6
    },
    {
      "date": "2025-09-30",
      "individual": -265,
      "foreign": 230,
      "institution": -497,
      "financialInvestment": -497,
      "insurance": 0,
      "investmentTrust": 0,
      "bank": 0,
      "otherFinancial": 0,
      "pension": 0,
      "otherCorporation": 532
    },
    {
      "date": "2025-10-01",
      "individual": -10812,
      "foreign": 8455,
      "institution": 2208,
      "financialInvestment": 2208,
      "insurance": 0,
      "investmentTrust": 0,
      "bank": 0,
      "otherFinancial": 0,
      "pension": 0,
      "otherCorporation": 149
    },
    {
      "date": "2025-10-02",
      "individual": -30715,
      "foreign": 31265,
      "institution": -675,
      "financialInvestment": -675,
      "insurance": 0,
      "investmentTrust": 0,
      "bank": 0,
      "otherFinancial": 0,
      "pension": 0,
      "otherCorporation": 125
    },
    {
      "date": "2025-10-10",
      "individual": -5022,
      "foreign": 10592,
      "institution": -5936,
      "financialInvestment": -5936,
      "insurance": 0,
      "investmentTrust": 0,
      "bank": 0,
      "otherFinancial": 0,
      "pension": 0,
      "otherCorporation": 366
    },
    {
      "date": "2025-10-13",
      "individual": 11649,
      "foreign": -8220,
      "institution": -4471,
      "financialInvestment": -4471,
      "insurance": 0,
      "investmentTrust": 0,
      "bank": 0,
      "otherFinancial": 0,
      "pension": 0,
      "otherCorporation": 1042
    },
    {
      "date": "2025-10-14",
      "individual": 20,
      "foreign": 5581,
      "institution": -6299,
      "financialInvestment": -6299,
      "insurance": 0,
      "investmentTrust": 0,
      "bank": 0,
      "otherFinancial": 0,
      "pension": 0,
      "otherCorporation": 698
    },
    {
      "date": "2025-10-15",
      "individual": -9706,
      "foreign": 1631,
      "institution": 7512,
      "financialInvestment": 7512,
      "insurance": 0,
      "investmentTrust": 0,
      "bank": 0,
      "otherFinancial": 0,
      "pension": 0,
      "otherCorporation": 563
    },
    {
      "date": "2025-10-16",
      "individual": -13936,
      "foreign": 6533,
      "institution": 7813,
      "financialInvestment": 7813,
      "insurance": 0,
      "investmentTrust": 0,
      "bank": 0,
      "otherFinancial": 0,
      "pension": 0,
      "otherCorporation": -410
    },
    {
      "date": "2025-10-17",
      "individual": -3122,
      "foreign": 4438,
      "institution": -1688,
      "financialInvestment": -1688,
      "insurance": 0,
      "investmentTrust": 0,
      "bank": 0,
      "otherFinancial": 0,
      "pension": 0,
      "otherCorporation": 372
    },
    {
      "date": "2025-10-20",
      "individual": -4109,
      "foreign": -2500,
      "institution": 6428,
      "financialInvestment": 6428,
      "insurance": 0,
      "investmentTrust": 0,
      "bank": 0,
      "otherFinancial": 0,
      "pension": 0,
      "otherCorporation": 181
    },
    {
      "date": "2025-10-21",
      "individual": -1556,
      "foreign": -124,
      "institution": 2116,
      "financialInvestment": 2116,
      "insurance": 0,
      "investmentTrust": 0,
      "bank": 0,
      "otherFinancial": 0,
      "pension": 0,
      "otherCorporation": -436
    },
    {
      "date": "2025-10-22",
      "individual": -769,
      "foreign": -7033,
      "institution": 7633,
      "financialInvestment": 7633,
      "insurance": 0,
      "investmentTrust": 0,
      "bank": 0,
      "otherFinancial": 0,
      "pension": 0,
      "otherCorporation": 169
    },
    {
      "date": "2025-10-23",
      "individual": 7505,
      "foreign": -4071,
      "institution": -3972,
      "financialInvestment": -3972,
      "insurance": 0,
      "investmentTrust": 0,
      "bank": 0,
      "otherFinancial": 0,
      "pension": 0,
      "otherCorporation": 538
    },
    {
      "date": "2025-10-24",
      "individual": -20005,
      "foreign": 5756,
      "institution": 14054,
      "financialInvestment": 14054,
      "insurance": 0,
      "investmentTrust": 0,
      "bank": 0,
      "otherFinancial": 0,
      "pension": 0,
      "otherCorporation": 195
    },
    {
      "date": "2025-10-27",
      "individual": -7969,
      "foreign": 6471,
      "institution": 2343,
      "financialInvestment": 2343,
      "insurance": 0,
      "investmentTrust": 0,
      "bank": 0,
      "otherFinancial": 0,
      "pension": 0,
      "otherCorporation": -845
    },
    {
      "date": "2025-10-28",
      "individual": 15728,
      "foreign": -16379,
      "institution": 925,
      "financialInvestment": 925,
      "insurance": 0,
      "investmentTrust": 0,
      "bank": 0,
      "otherFinancial": 0,
      "pension": 0,
      "otherCorporation": -274
    },
    {
      "date": "2025-10-29",
      "individual": -3583,
      "foreign": -1066,
      "institution": 5196,
      "financialInvestment": 5196,
      "insurance": 0,
      "investmentTrust": 0,
      "bank": 0,
      "otherFinancial": 0,
      "pension": 0,
      "otherCorporation": -547
    },
    {
      "date": "2025-10-30",
      "individual": 9363,
      "foreign": -1173,
      "institution": -8379,
      "financialInvestment": -8379,
      "insurance": 0,
      "investmentTrust": 0,
      "bank": 0,
      "otherFinancial": 0,
      "pension": 0,
      "otherCorporation": 189
    },
    {
      "date": "2025-10-31",
      "individual": -2018,
      "foreign": 13212,
      "institution": -11064,
      "financialInvestment": -11064,
      "insurance": 0,
      "investmentTrust": 0,
      "bank": 0,
      "otherFinancial": 0,
      "pension": 0,
      "otherCorporation": -130
    },
    {
      "date": "2025-11-03",
      "individual": 6256,
      "foreign": -7949,
      "institution": 1841,
      "financialInvestment": 1841,
      "insurance": 0,
      "investmentTrust": 0,
      "bank": 0,
      "otherFinancial": 0,
      "pension": 0,
      "otherCorporation": -148
    },
    {
      "date": "2025-11-04",
      "individual": 27009,
      "foreign": -22282,
      "institution": -4989,
      "financialInvestment": -4989,
      "insurance": 0,
      "investmentTrust": 0,
      "bank": 0,
      "otherFinancial": 0,
      "pension": 0,
      "otherCorporation": 262
    },
    {
      "date": "2025-11-05",
      "individual": 25538,
      "foreign": -20695,
      "institution": -1877,
      "financialInvestment": -1877,
      "insurance": 0,
      "investmentTrust": 0,
      "bank": 0,
      "otherFinancial": 0,
      "pension": 0,
      "otherCorporation": -2966
    },
    {
      "date": "2025-11-06",
      "individual": 8840,
      "foreign": -16950,
      "institution": 8301,
      "financialInvestment": 8301,
      "insurance": 0,
      "investmentTrust": 0,
      "bank": 0,
      "otherFinancial": 0,
      "pension": 0,
      "otherCorporation": -191
    },
    {
      "date": "2025-11-07",
      "individual": 6791,
      "foreign": -4550,
      "institution": -2446,
      "financialInvestment": -2446,
      "insurance": 0,
      "investmentTrust": 0,
      "bank": 0,
      "otherFinancial": 0,
      "pension": 0,
      "otherCorporation": 205
    },
    {
      "date": "2025-11-10",
      "individual": -11607,
      "foreign": -1510,
      "institution": 13066,
      "financialInvestment": 13066,
      "insurance": 0,
      "investmentTrust": 0,
      "bank": 0,
      "otherFinancial": 0,
      "pension": 0,
      "otherCorporation": 51
    },
    {
      "date": "2025-11-11",
      "individual": -2831,
      "foreign": 770,
      "institution": 2247,
      "financialInvestment": 2247,
      "insurance": 0,
      "investmentTrust": 0,
      "bank": 0,
      "otherFinancial": 0,
      "pension": 0,
      "otherCorporation": -186
    },
    {
      "date": "2025-11-12",
      "individual": -4423,
      "foreign": -4265,
      "institution": 9093,
      "financialInvestment": 9093,
      "insurance": 0,
      "investmentTrust": 0,
      "bank": 0,
      "otherFinancial": 0,
      "pension": 0,
      "otherCorporation": -405
    },
    {
      "date": "2025-11-13",
      "individual": -2343,
      "foreign": 9989,
      "institution": -7179,
      "financialInvestment": -7179,
      "insurance": 0,
      "investmentTrust": 0,
      "bank": 0,
      "otherFinancial": 0,
      "pension": 0,
      "otherCorporation": -467
    },
    {
      "date": "2025-11-14",
      "individual": 32346,
      "foreign": -23575,
      "institution": -9005,
      "financialInvestment": -9005,
      "insurance": 0,
      "investmentTrust": 0,
      "bank": 0,
      "otherFinancial": 0,
      "pension": 0,
      "otherCorporation": 234
    },
    {
      "date": "2025-11-17",
      "individual": -5000,
      "foreign": 5189,
      "institution": -245,
      "financialInvestment": -245,
      "insurance": 0,
      "investmentTrust": 0,
      "bank": 0,
      "otherFinancial": 0,
      "pension": 0,
      "otherCorporation": 56
    },
    {
      "date": "2025-11-18",
      "individual": 12382,
      "foreign": -5500,
      "institution": -6788,
      "financialInvestment": -6788,
      "insurance": 0,
      "investmentTrust": 0,
      "bank": 0,
      "otherFinancial": 0,
      "pension": 0,
      "otherCorporation": -94
    },
    {
      "date": "2025-11-19",
      "individual": 4450,
      "foreign": -10495,
      "institution": 6256,
      "financialInvestment": 6256,
      "insurance": 0,
      "investmentTrust": 0,
      "bank": 0,
      "otherFinancial": 0,
      "pension": 0,
      "otherCorporation": -211
    },
    {
      "date": "2025-11-20",
      "individual": -13817,
      "foreign": 7406,
      "institution": 7566,
      "financialInvestment": 7566,
      "insurance": 0,
      "investmentTrust": 0,
      "bank": 0,
      "otherFinancial": 0,
      "pension": 0,
      "otherCorporation": -1155
    },
    {
      "date": "2025-11-21",
      "individual": 22695,
      "foreign": -28229,
      "institution": 4935,
      "financialInvestment": 4935,
      "insurance": 0,
      "investmentTrust": 0,
      "bank": 0,
      "otherFinancial": 0,
      "pension": 0,
      "otherCorporation": 599
    },
    {
      "date": "2025-11-24",
      "individual": -4619,
      "foreign": -7993,
      "institution": 12719,
      "financialInvestment": 12719,
      "insurance": 0,
      "investmentTrust": 0,
      "bank": 0,
      "otherFinancial": 0,
      "pension": 0,
      "otherCorporation": -107
    },
    {
      "date": "2025-11-25",
      "individual": -276,
      "foreign": 49,
      "institution": 315,
      "financialInvestment": 315,
      "insurance": 0,
      "investmentTrust": 0,
      "bank": 0,
      "otherFinancial": 0,
      "pension": 0,
      "otherCorporation": -88
    },
    {
      "date": "2025-11-26",
      "individual": -18048,
      "foreign": 5158,
      "institution": 12280,
      "financialInvestment": 12280,
      "insurance": 0,
      "investmentTrust": 0,
      "bank": 0,
      "otherFinancial": 0,
      "pension": 0,
      "otherCorporation": 610
    },
    {
      "date": "2025-11-27",
      "individual": -6152,
      "foreign": 1546,
      "institution": 4326,
      "financialInvestment": 4326,
      "insurance": 0,
      "investmentTrust": 0,
      "bank": 0,
      "otherFinancial": 0,
      "pension": 0,
      "otherCorporation": 280
    },
    {
      "date": "2025-11-28",
      "individual": 15685,
      "foreign": -20369,
      "institution": 4587,
      "financialInvestment": 4587,
      "insurance": 0,
      "investmentTrust": 0,
      "bank": 0,
      "otherFinancial": 0,
      "pension": 0,
      "otherCorporation": 97
    },
    {
      "date": "2025-12-01",
      "individual": 529,
      "foreign": 2235,
      "institution": -2333,
      "financialInvestment": -2333,
      "insurance": 0,
      "investmentTrust": 0,
      "bank": 0,
      "otherFinancial": 0,
      "pension": 0,
      "otherCorporation": -431
    },
    {
      "date": "2025-12-02",
      "individual": -15763,
      "foreign": 12147,
      "institution": 3929,
      "financialInvestment": 3929,
      "insurance": 0,
      "investmentTrust": 0,
      "bank": 0,
      "otherFinancial": 0,
      "pension": 0,
      "otherCorporation": -313
    },
    {
      "date": "2025-12-03",
      "individual": -8984,
      "foreign": 2816,
      "institution": 7364,
      "financialInvestment": 7364,
      "insurance": 0,
      "investmentTrust": 0,
      "bank": 0,
      "otherFinancial": 0,
      "pension": 0,
      "otherCorporation": -1196
    },
    {
      "date": "2025-12-04",
      "individual": 5585,
      "foreign": -6960,
      "institution": 1318,
      "financialInvestment": 1318,
      "insurance": 0,
      "investmentTrust": 0,
      "bank": 0,
      "otherFinancial": 0,
      "pension": 0,
      "otherCorporation": 57
    },
    {
      "date": "2025-12-05",
      "individual": -21156,
      "foreign": 9934,
      "institution": 11528,
      "financialInvestment": 11528,
      "insurance": 0,
      "investmentTrust": 0,
      "bank": 0,
      "otherFinancial": 0,
      "pension": 0,
      "otherCorporation": -306
    },
    {
      "date": "2025-12-08",
      "individual": -3449,
      "foreign": 3211,
      "institution": -308,
      "financialInvestment": -308,
      "insurance": 0,
      "investmentTrust": 0,
      "bank": 0,
      "otherFinancial": 0,
      "pension": 0,
      "otherCorporation": 546
    },
    {
      "date": "2025-12-09",
      "individual": -133,
      "foreign": -889,
      "institution": 494,
      "financialInvestment": 494,
      "insurance": 0,
      "investmentTrust": 0,
      "bank": 0,
      "otherFinancial": 0,
      "pension": 0,
      "otherCorporation": 528
    },
    {
      "date": "2025-12-10",
      "individual": -889,
      "foreign": 3739,
      "institution": -3003,
      "financialInvestment": -3003,
      "insurance": 0,
      "investmentTrust": 0,
      "bank": 0,
      "otherFinancial": 0,
      "pension": 0,
      "otherCorporation": 153
    },
    {
      "date": "2025-12-11",
      "individual": 3922,
      "foreign": 3656,
      "institution": -7753,
      "financialInvestment": -7753,
      "insurance": 0,
      "investmentTrust": 0,
      "bank": 0,
      "otherFinancial": 0,
      "pension": 0,
      "otherCorporation": 175
    },
    {
      "date": "2025-12-12",
      "individual": -14625,
      "foreign": 414,
      "institution": 14184,
      "financialInvestment": 14184,
      "insurance": 0,
      "investmentTrust": 0,
      "bank": 0,
      "otherFinancial": 0,
      "pension": 0,
      "otherCorporation": 27
    },
    {
      "date": "2025-12-15",
      "individual": 14210,
      "foreign": -9569,
      "institution": -4803,
      "financialInvestment": -4803,
      "insurance": 0,
      "investmentTrust": 0,
      "bank": 0,
      "otherFinancial": 0,
      "pension": 0,
      "otherCorporation": 162
    },
    {
      "date": "2025-12-16",
      "individual": 12410,
      "foreign": -10305,
      "institution": -2309,
      "financialInvestment": -2309,
      "insurance": 0,
      "investmentTrust": 0,
      "bank": 0,
      "otherFinancial": 0,
      "pension": 0,
      "otherCorporation": 204
    },
    {
      "date": "2025-12-17",
      "individual": -3374,
      "foreign": -322,
      "institution": 3353,
      "financialInvestment": 3353,
      "insurance": 0,
      "investmentTrust": 0,
      "bank": 0,
      "otherFinancial": 0,
      "pension": 0,
      "otherCorporation": 343
    },
    {
      "date": "2025-12-18",
      "individual": 4130,
      "foreign": -3459,
      "institution": -1006,
      "financialInvestment": -1006,
      "insurance": 0,
      "investmentTrust": 0,
      "bank": 0,
      "otherFinancial": 0,
      "pension": 0,
      "otherCorporation": 335
    },
    {
      "date": "2025-12-19",
      "individual": -1413,
      "foreign": -7573,
      "institution": 8541,
      "financialInvestment": 8541,
      "insurance": 0,
      "investmentTrust": 0,
      "bank": 0,
      "otherFinancial": 0,
      "pension": 0,
      "otherCorporation": 445
    },
    {
      "date": "2025-12-22",
      "individual": -26714,
      "foreign": 11017,
      "institution": 16055,
      "financialInvestment": 16055,
      "insurance": 0,
      "investmentTrust": 0,
      "bank": 0,
      "otherFinancial": 0,
      "pension": 0,
      "otherCorporation": -358
    },
    {
      "date": "2025-12-23",
      "individual": -12853,
      "foreign": 9551,
      "institution": 3527,
      "financialInvestment": 3527,
      "insurance": 0,
      "investmentTrust": 0,
      "bank": 0,
      "otherFinancial": 0,
      "pension": 0,
      "otherCorporation": -225
    },
    {
      "date": "2025-12-24",
      "individual": -7171,
      "foreign": 5225,
      "institution": 2039,
      "financialInvestment": 2039,
      "insurance": 0,
      "investmentTrust": 0,
      "bank": 0,
      "otherFinancial": 0,
      "pension": 0,
      "otherCorporation": -93
    },
    {
      "date": "2025-12-26",
      "individual": -23265,
      "foreign": 17790,
      "institution": 4435,
      "financialInvestment": 4435,
      "insurance": 0,
      "investmentTrust": 0,
      "bank": 0,
      "otherFinancial": 0,
      "pension": 0,
      "otherCorporation": 1040
    },
    {
      "date": "2025-12-29",
      "individual": 661,
      "foreign": 3337,
      "institution": -3133,
      "financialInvestment": -3133,
      "insurance": 0,
      "investmentTrust": 0,
      "bank": 0,
      "otherFinancial": 0,
      "pension": 0,
      "otherCorporation": -865
    },
    {
      "date": "2025-12-30",
      "individual": 8448,
      "foreign": -4768,
      "institution": -3763,
      "financialInvestment": -3763,
      "insurance": 0,
      "investmentTrust": 0,
      "bank": 0,
      "otherFinancial": 0,
      "pension": 0,
      "otherCorporation": 83
    },
    {
      "date": "2026-01-02",
      "individual": -4252,
      "foreign": 6309,
      "institution": -2477,
      "financialInvestment": -2477,
      "insurance": 0,
      "investmentTrust": 0,
      "bank": 0,
      "otherFinancial": 0,
      "pension": 0,
      "otherCorporation": 420
    },
    {
      "date": "2026-01-05",
      "individual": -15141,
      "foreign": 21726,
      "institution": -7046,
      "financialInvestment": -7046,
      "insurance": 0,
      "investmentTrust": 0,
      "bank": 0,
      "otherFinancial": 0,
      "pension": 0,
      "otherCorporation": 461
    },
    {
      "date": "2026-01-06",
      "individual": 5963,
      "foreign": -6184,
      "institution": -664,
      "financialInvestment": -664,
      "insurance": 0,
      "investmentTrust": 0,
      "bank": 0,
      "otherFinancial": 0,
      "pension": 0,
      "otherCorporation": 885
    },
    {
      "date": "2026-01-07",
      "individual": -2944,
      "foreign": 12548,
      "institution": -9397,
      "financialInvestment": -9397,
      "insurance": 0,
      "investmentTrust": 0,
      "bank": 0,
      "otherFinancial": 0,
      "pension": 0,
      "otherCorporation": -207
    },
    {
      "date": "2026-01-08",
      "individual": 12540,
      "foreign": -979,
      "institution": -14014,
      "financialInvestment": -14014,
      "insurance": 0,
      "investmentTrust": 0,
      "bank": 0,
      "otherFinancial": 0,
      "pension": 0,
      "otherCorporation": 2453
    },
    {
      "date": "2026-01-09",
      "individual": 1339,
      "foreign": -16068,
      "institution": 12046,
      "financialInvestment": 12046,
      "insurance": 0,
      "investmentTrust": 0,
      "bank": 0,
      "otherFinancial": 0,
      "pension": 0,
      "otherCorporation": 2683
    },
    {
      "date": "2026-01-12",
      "individual": -1013,
      "foreign": -3512,
      "institution": 2101,
      "financialInvestment": 2101,
      "insurance": 0,
      "investmentTrust": 0,
      "bank": 0,
      "otherFinancial": 0,
      "pension": 0,
      "otherCorporation": 2424
    },
    {
      "date": "2026-01-13",
      "individual": -7125,
      "foreign": -2793,
      "institution": 7881,
      "financialInvestment": 7881,
      "insurance": 0,
      "investmentTrust": 0,
      "bank": 0,
      "otherFinancial": 0,
      "pension": 0,
      "otherCorporation": 2037
    },
    {
      "date": "2026-01-14",
      "individual": -4377,
      "foreign": -3760,
      "institution": 5887,
      "financialInvestment": 5887,
      "insurance": 0,
      "investmentTrust": 0,
      "bank": 0,
      "otherFinancial": 0,
      "pension": 0,
      "otherCorporation": 2250
    },
    {
      "date": "2026-01-15",
      "individual": -18235,
      "foreign": 3450,
      "institution": 12905,
      "financialInvestment": 12905,
      "insurance": 0,
      "investmentTrust": 0,
      "bank": 0,
      "otherFinancial": 0,
      "pension": 0,
      "otherCorporation": 1880
    },
    {
      "date": "2026-01-16",
      "individual": -9383,
      "foreign": 4350,
      "institution": 3083,
      "financialInvestment": 3083,
      "insurance": 0,
      "investmentTrust": 0,
      "bank": 0,
      "otherFinancial": 0,
      "pension": 0,
      "otherCorporation": 1950
    },
    {
      "date": "2026-01-19",
      "individual": -7513,
      "foreign": 5532,
      "institution": -256,
      "financialInvestment": -256,
      "insurance": 0,
      "investmentTrust": 0,
      "bank": 0,
      "otherFinancial": 0,
      "pension": 0,
      "otherCorporation": 2237
    },
    {
      "date": "2026-01-20",
      "individual": 3524,
      "foreign": 1232,
      "institution": -6500,
      "financialInvestment": -6500,
      "insurance": 0,
      "investmentTrust": 0,
      "bank": 0,
      "otherFinancial": 0,
      "pension": 0,
      "otherCorporation": 1744
    },
    {
      "date": "2026-01-21",
      "individual": -9965,
      "foreign": 4394,
      "institution": 3217,
      "financialInvestment": 3217,
      "insurance": 0,
      "investmentTrust": 0,
      "bank": 0,
      "otherFinancial": 0,
      "pension": 0,
      "otherCorporation": 2354
    },
    {
      "date": "2026-01-22",
      "individual": 1555,
      "foreign": -2432,
      "institution": -1568,
      "financialInvestment": -1568,
      "insurance": 0,
      "investmentTrust": 0,
      "bank": 0,
      "otherFinancial": 0,
      "pension": 0,
      "otherCorporation": 2445
    },
    {
      "date": "2026-01-23",
      "individual": -7239,
      "foreign": 1438,
      "institution": 4790,
      "financialInvestment": 4790,
      "insurance": 0,
      "investmentTrust": 0,
      "bank": 0,
      "otherFinancial": 0,
      "pension": 0,
      "otherCorporation": 1011
    },
    {
      "date": "2026-01-26",
      "individual": 17157,
      "foreign": -1588,
      "institution": -15414,
      "financialInvestment": -15414,
      "insurance": 0,
      "investmentTrust": 0,
      "bank": 0,
      "otherFinancial": 0,
      "pension": 0,
      "otherCorporation": -155
    },
    {
      "date": "2026-01-27",
      "individual": -10197,
      "foreign": 8448,
      "institution": 2474,
      "financialInvestment": 2474,
      "insurance": 0,
      "investmentTrust": 0,
      "bank": 0,
      "otherFinancial": 0,
      "pension": 0,
      "otherCorporation": -725
    },
    {
      "date": "2026-01-28",
      "individual": 12131,
      "foreign": 4008,
      "institution": -14021,
      "financialInvestment": -14021,
      "insurance": 0,
      "investmentTrust": 0,
      "bank": 0,
      "otherFinancial": 0,
      "pension": 0,
      "otherCorporation": -2118
    },
    {
      "date": "2026-01-29",
      "individual": 16173,
      "foreign": -14897,
      "institution": -1673,
      "financialInvestment": -1673,
      "insurance": 0,
      "investmentTrust": 0,
      "bank": 0,
      "otherFinancial": 0,
      "pension": 0,
      "otherCorporation": 397
    },
    {
      "date": "2026-01-30",
      "individual": 22979,
      "foreign": -19729,
      "institution": -4241,
      "financialInvestment": -4241,
      "insurance": 0,
      "investmentTrust": 0,
      "bank": 0,
      "otherFinancial": 0,
      "pension": 0,
      "otherCorporation": 991
    },
    {
      "date": "2026-02-02",
      "individual": 45874,
      "foreign": -25168,
      "institution": -22125,
      "financialInvestment": -22125,
      "insurance": 0,
      "investmentTrust": 0,
      "bank": 0,
      "otherFinancial": 0,
      "pension": 0,
      "otherCorporation": 1419
    },
    {
      "date": "2026-02-03",
      "individual": -29423,
      "foreign": 7038,
      "institution": 21708,
      "financialInvestment": 21708,
      "insurance": 0,
      "investmentTrust": 0,
      "bank": 0,
      "otherFinancial": 0,
      "pension": 0,
      "otherCorporation": 677
    },
    {
      "date": "2026-02-04",
      "individual": -10119,
      "foreign": -9413,
      "institution": 17836,
      "financialInvestment": 17836,
      "insurance": 0,
      "investmentTrust": 0,
      "bank": 0,
      "otherFinancial": 0,
      "pension": 0,
      "otherCorporation": 1696
    },
    {
      "date": "2026-02-05",
      "individual": 67791,
      "foreign": -50108,
      "institution": -20693,
      "financialInvestment": -20693,
      "insurance": 0,
      "investmentTrust": 0,
      "bank": 0,
      "otherFinancial": 0,
      "pension": 0,
      "otherCorporation": 3010
    },
    {
      "date": "2026-02-06",
      "individual": 21736,
      "foreign": -33233,
      "institution": 9414,
      "financialInvestment": 9414,
      "insurance": 0,
      "investmentTrust": 0,
      "bank": 0,
      "otherFinancial": 0,
      "pension": 0,
      "otherCorporation": 2083
    },
    {
      "date": "2026-02-09",
      "individual": -32947,
      "foreign": 4320,
      "institution": 27123,
      "financialInvestment": 27123,
      "insurance": 0,
      "investmentTrust": 0,
      "bank": 0,
      "otherFinancial": 0,
      "pension": 0,
      "otherCorporation": 1504
    },
    {
      "date": "2026-02-10",
      "individual": -8780,
      "foreign": 1474,
      "institution": 5643,
      "financialInvestment": 5643,
      "insurance": 0,
      "investmentTrust": 0,
      "bank": 0,
      "otherFinancial": 0,
      "pension": 0,
      "otherCorporation": 1663
    },
    {
      "date": "2026-02-11",
      "individual": -17149,
      "foreign": 8461,
      "institution": 6927,
      "financialInvestment": 6927,
      "insurance": 0,
      "investmentTrust": 0,
      "bank": 0,
      "otherFinancial": 0,
      "pension": 0,
      "otherCorporation": 1761
    },
    {
      "date": "2026-02-12",
      "individual": -44547,
      "foreign": 29954,
      "institution": 13800,
      "financialInvestment": 13800,
      "insurance": 0,
      "investmentTrust": 0,
      "bank": 0,
      "otherFinancial": 0,
      "pension": 0,
      "otherCorporation": 793
    },
    {
      "date": "2026-02-13",
      "individual": 7141,
      "foreign": -9220,
      "institution": 831,
      "financialInvestment": 831,
      "insurance": 0,
      "investmentTrust": 0,
      "bank": 0,
      "otherFinancial": 0,
      "pension": 0,
      "otherCorporation": 1248
    },
    {
      "date": "2026-02-19",
      "individual": -8609,
      "foreign": -9396,
      "institution": 16542,
      "financialInvestment": 16542,
      "insurance": 0,
      "investmentTrust": 0,
      "bank": 0,
      "otherFinancial": 0,
      "pension": 0,
      "otherCorporation": 1463
    },
    {
      "date": "2026-02-20",
      "individual": -9873,
      "foreign": -7420,
      "institution": 16149,
      "financialInvestment": 16149,
      "insurance": 0,
      "investmentTrust": 0,
      "bank": 0,
      "otherFinancial": 0,
      "pension": 0,
      "otherCorporation": 1144
    },
    {
      "date": "2026-02-23",
      "individual": 10815,
      "foreign": -11132,
      "institution": -1271,
      "financialInvestment": -1271,
      "insurance": 0,
      "investmentTrust": 0,
      "bank": 0,
      "otherFinancial": 0,
      "pension": 0,
      "otherCorporation": 1588
    },
    {
      "date": "2026-02-24",
      "individual": -22861,
      "foreign": -2013,
      "institution": 23773,
      "financialInvestment": 23773,
      "insurance": 0,
      "investmentTrust": 0,
      "bank": 0,
      "otherFinancial": 0,
      "pension": 0,
      "otherCorporation": 1101
    },
    {
      "date": "2026-02-25",
      "individual": 2307,
      "foreign": -13082,
      "institution": 14701,
      "financialInvestment": 14701,
      "insurance": 0,
      "investmentTrust": 0,
      "bank": 0,
      "otherFinancial": 0,
      "pension": 0,
      "otherCorporation": -3926
    },
    {
      "date": "2026-02-26",
      "individual": 6498,
      "foreign": -21135,
      "institution": 12569,
      "financialInvestment": 12569,
      "insurance": 0,
      "investmentTrust": 0,
      "bank": 0,
      "otherFinancial": 0,
      "pension": 0,
      "otherCorporation": 2068
    },
    {
      "date": "2026-02-27",
      "individual": 62496,
      "foreign": -70528,
      "institution": 5666,
      "financialInvestment": 5666,
      "insurance": 0,
      "investmentTrust": 0,
      "bank": 0,
      "otherFinancial": 0,
      "pension": 0,
      "otherCorporation": 2366
    }
  ]
}
